pycrosskit/__init__.py
pycrosskit/__version__.py
pycrosskit/constants.py
pycrosskit/envariables.py
pycrosskit/shortcuts.py
pycrosskit/env_platforms/__init__.py
pycrosskit/env_platforms/exceptions.py
pycrosskit/env_platforms/linux.py
pycrosskit/env_platforms/windows.py
pycrosskit/shortcut_platforms/__init__.py
pycrosskit/shortcut_platforms/linux.py
pycrosskit/shortcut_platforms/windows.py
tests/__init__.py
tests/test_env_vars_linux.py
tests/test_env_vars_windows.py
tests/test_shortcut.py
pycrosskit-1.7.5.dist-info/LICENSE.md
pycrosskit-1.7.5.dist-info/METADATA
pycrosskit-1.7.5.dist-info/WHEEL
pycrosskit-1.7.5.dist-info/entry_points.txt
pycrosskit-1.7.5.dist-info/top_level.txt
pycrosskit-1.7.5.dist-info/zip-safe
pycrosskit-1.7.5.dist-info/RECORD
