Metadata-Version: 2.1
Name: pycrosskit
Version: 1.7.5
Summary: Cross Platform Toolkit for Windows and Linux in order to make variables and shortcuts easy 
Home-page: https://github.com/jiri-otoupal/py-cross-kit
Author: Jiri Otoupal
Author-email: jiri-otoupal@ips-database.eu
License: Apache 2.0
Keywords: Python Cross Platform Toolkit
Classifier: Development Status :: 4 - Beta
Classifier: Intended Audience :: Developers
Classifier: Programming Language :: Python :: 3.7
Classifier: Programming Language :: Python :: 3.8
Classifier: Programming Language :: Python :: 3.9
Classifier: Programming Language :: Python :: 3.10
Classifier: Programming Language :: Python :: 3.11
Requires-Python: >=3.7,<4
License-File: LICENSE.md
Requires-Dist: pywin32 >=300 ; sys_platform == "win32"
Provides-Extra: dev
Requires-Dist: black <24,>=22 ; extra == 'dev'
Requires-Dist: flake8 <6.1 ; extra == 'dev'
Requires-Dist: pre-commit <3.3 ; extra == 'dev'
Requires-Dist: pytest <7.5 ; extra == 'dev'
